gdbus_util/__init__.py
gdbus_util/dbus_object.py
gdbus_util/error.py
gdbus_util/exit_on_idle.py
gdbus_util-0.1.0.dist-info/METADATA
gdbus_util-0.1.0.dist-info/WHEEL
gdbus_util-0.1.0.dist-info/licenses/LICENSE
gdbus_util-0.1.0.dist-info/RECORD
