Metadata-Version: 2.1
Name: gdbus-util
Version: 0.1.0
Summary: Easy GDBus service creation with exit-on-idle functionality.
Project-URL: Documentation, https://python-gdbus-util.readthedocs.io/en/latest/
Project-URL: Source, https://github.com/adombeck/python-gdbus-util
Author-email: Adrian Dombeck <adrian.dombeck@gmail.com>
License-File: LICENSE
Classifier: License :: OSI Approved :: GNU General Public License v3 (GPLv3)
Classifier: Operating System :: POSIX :: Linux
Classifier: Programming Language :: Python :: 3
Requires-Python: >=3.11
